fealty/__init__.py
fealty/field_numerics.c
fealty/field_numerics.pyx
fealty/field_numerics.so
fealty/fields.py
fealty/lattice.py
fealty/lattice_numerics.c
fealty/lattice_numerics.pyx
fealty/lattice_numerics.so
fealty/walled_field_numerics.c
fealty/walled_field_numerics.pyx
fealty/walled_field_numerics.so
fealty-0.1.2.dist-info/DESCRIPTION.rst
fealty-0.1.2.dist-info/METADATA
fealty-0.1.2.dist-info/metadata.json
fealty-0.1.2.dist-info/pbr.json
fealty-0.1.2.dist-info/RECORD
fealty-0.1.2.dist-info/top_level.txt
fealty-0.1.2.dist-info/WHEEL
