Metadata-Version: 2.0
Name: fealty
Version: 0.1.2
Summary: Discretised field utilities
Home-page: https://github.com/eddiejessup/fealty
Author: Elliot Marsden
Author-email: elliot.marsden@gmail.com
License: BSD
Keywords: fealty
Platform: UNKNOWN
Classifier: Development Status :: 4 - Beta
Classifier: Intended Audience :: Science/Research
Classifier: Topic :: Scientific/Engineering
Classifier: License :: OSI Approved :: BSD License
Classifier: Natural Language :: English
Classifier: Programming Language :: Python :: 2
Classifier: Programming Language :: Python :: 2.6
Classifier: Programming Language :: Python :: 2.7
Classifier: Programming Language :: Python :: 3
Classifier: Programming Language :: Python :: 3.3
Classifier: Programming Language :: Python :: 3.4
Requires-Dist: Cython
Requires-Dist: numpy
Requires-Dist: ciabatta
